DESCRIPTION
MANIFEST.in
README
README.rst
setup.py
django_zenforms.egg-info/PKG-INFO
django_zenforms.egg-info/SOURCES.txt
django_zenforms.egg-info/dependency_links.txt
django_zenforms.egg-info/not-zip-safe
django_zenforms.egg-info/requires.txt
django_zenforms.egg-info/top_level.txt
zenforms/__init__.py
zenforms/static/zenforms/css/blue.uni-form.css
zenforms/static/zenforms/css/dark.uni-form.css
zenforms/static/zenforms/css/default.uni-form.css
zenforms/static/zenforms/css/ready.uni-form.css
zenforms/static/zenforms/css/uni-form.css
zenforms/static/zenforms/js/uni-form-validation.jquery.js
zenforms/static/zenforms/js/uni-form-validation.jquery.min.js
zenforms/static/zenforms/js/uni-form.jquery.js
zenforms/static/zenforms/js/uni-form.jquery.min.js
zenforms/static/zenforms/js/localization/da.js
zenforms/static/zenforms/js/localization/de.js
zenforms/static/zenforms/js/localization/es.js
zenforms/static/zenforms/js/localization/fi.js
zenforms/static/zenforms/js/localization/fr.js
zenforms/static/zenforms/js/localization/it.js
zenforms/static/zenforms/js/localization/tr.js
zenforms/templates/zenforms/field.html
zenforms/templates/zenforms/fieldset.html
zenforms/templates/zenforms/submit.html
zenforms/templates/zenforms/zenform_inline.html
zenforms/templates/zenforms/zenform_postfix.html
zenforms/templates/zenforms/zenform_prefix.html
zenforms/templates/zenforms/fields/multi.html
zenforms/templates/zenforms/fields/readonly.html
zenforms/templates/zenforms/fields/single.html
zenforms/templatetags/__init__.py
zenforms/templatetags/zenforms.py