Metadata-Version: 1.0
Name: django-zenforms
Version: 0.1.2
Summary: Application allows you to control forms layout from templates. Uniforms batteries included.
Home-page: http://github.com/summerisgone/zenforms
Author: Ivan Gromov
Author-email: ivan.gromov@redsolution.ru
License: GPL
Keywords: django forms zen uniform
Platform: UNKNOWN
Classifier: Development Status :: 3 - Alpha
Classifier: Intended Audience :: Developers
Classifier: License :: OSI Approved :: GNU General Public License (GPL)
Classifier: Framework :: Django
Classifier: Environment :: Web Environment
Classifier: Natural Language :: Russian
Classifier: Natural Language :: English
Classifier: Operating System :: OS Independent
Classifier: Programming Language :: Python
Classifier: Topic :: Internet :: WWW/HTTP :: Dynamic Content
